itk/StrainPython.py
itk/_StrainPython.pyd
itk/__init_strain__.py
itk/itkStrainImageFilterPython.py
itk/itkTransformToStrainFilterPython.py
itk/Configuration/StrainConfig.py
itk/Configuration/Strain_snake_case.py
itk_strain-1.0.1.dist-info/licenses/LICENSE
itk_strain.libs/msvcp140.dll
itk_strain.libs/tbb12.dll
itk_strain-1.0.1.dist-info/DELVEWHEEL
itk_strain-1.0.1.dist-info/METADATA
itk_strain-1.0.1.dist-info/WHEEL
itk_strain-1.0.1.dist-info/RECORD
